create_react_app/__init__.py
create_react_app/admin.py
create_react_app/apps.py
create_react_app/asset.py
create_react_app/config.py
create_react_app/exception.py
create_react_app/loader.py
create_react_app/models.py
create_react_app/tests.py
create_react_app/utils.py
create_react_app/views.py
create_react_app/templatetags/__init__.py
create_react_app/templatetags/react_bundle_loader.py
django_create_react_app-0.9.0.dist-info/METADATA
django_create_react_app-0.9.0.dist-info/WHEEL
django_create_react_app-0.9.0.dist-info/top_level.txt
django_create_react_app-0.9.0.dist-info/RECORD
