Metadata-Version: 2.1
Name: django-create-react-app
Version: 0.9.0
Summary: use create react app with django
Home-page: https://github.com/aamirbhat/django-create-react-app.git
Author: Aamir Bhat
Author-email: aamirbhat.pro@gmail.com
License: UNKNOWN
Keywords: django,create-react-app,react,django react,django integration  react, create react app
Platform: UNKNOWN
Classifier: Programming Language :: Python :: 2.6
Classifier: Programming Language :: Python :: 2.7
Classifier: Programming Language :: Python :: 3.3
Classifier: Programming Language :: Python :: 3.4
Classifier: Programming Language :: Python :: 3.5
Classifier: Framework :: Django
Classifier: Environment :: Web Environment
Classifier: License :: OSI Approved :: MIT License
Requires-Dist: requests
